odoo/addons/base_kardex/LICENSE
odoo/addons/base_kardex/README.rst
odoo/addons/base_kardex/__init__.py
odoo/addons/base_kardex/__manifest__.py
odoo/addons/base_kardex/images/screen.png
odoo/addons/base_kardex/models/__init__.py
odoo/addons/base_kardex/models/base_kardex_mixin.py
odoo/addons/base_kardex/models/base_kardex_settings.py
odoo/addons/base_kardex/security/ir.model.access.csv
odoo/addons/base_kardex/static/description/icon.png
odoo/addons/base_kardex/static/description/index.html
odoo/addons/base_kardex/static/src/css/style.css
odoo/addons/base_kardex/static/src/js/widget.js
odoo_addon_base_kardex-18.0.1.0.0.dist-info/METADATA
odoo_addon_base_kardex-18.0.1.0.0.dist-info/WHEEL
odoo_addon_base_kardex-18.0.1.0.0.dist-info/top_level.txt
odoo_addon_base_kardex-18.0.1.0.0.dist-info/RECORD
